karbor_dashboard/__init__.py
karbor_dashboard/dashboard.py
karbor_dashboard/version.py
karbor_dashboard/views.py
karbor_dashboard/api/__init__.py
karbor_dashboard/api/karbor.py
karbor_dashboard/api/rest/__init__.py
karbor_dashboard/checkpoints/__init__.py
karbor_dashboard/checkpoints/forms.py
karbor_dashboard/checkpoints/panel.py
karbor_dashboard/checkpoints/tables.py
karbor_dashboard/checkpoints/urls.py
karbor_dashboard/checkpoints/utils.py
karbor_dashboard/checkpoints/views.py
karbor_dashboard/enabled/_6000_data_protection.py
karbor_dashboard/enabled/_6010_data_protection_protection_plans_panel.py
karbor_dashboard/enabled/_6020_data_protection_protection_providers_panel.py
karbor_dashboard/enabled/_6030_data_protection_checkpoints_panel.py
karbor_dashboard/enabled/_6040_data_protection_operation_logs_panel.py
karbor_dashboard/enabled/_6050_data_protection_triggers_panel.py
karbor_dashboard/enabled/_6060_data_protection_restores_panel.py
karbor_dashboard/enabled/_6070_data_protection_scheduled_operations_panel.py
karbor_dashboard/enabled/__init__.py
karbor_dashboard/locale/de/LC_MESSAGES/django.po
karbor_dashboard/locale/en_GB/LC_MESSAGES/django.po
karbor_dashboard/locale/id/LC_MESSAGES/django.po
karbor_dashboard/locale/ko_KR/LC_MESSAGES/django.po
karbor_dashboard/operationlogs/__init__.py
karbor_dashboard/operationlogs/panel.py
karbor_dashboard/operationlogs/tables.py
karbor_dashboard/operationlogs/urls.py
karbor_dashboard/operationlogs/views.py
karbor_dashboard/protectionplans/__init__.py
karbor_dashboard/protectionplans/forms.py
karbor_dashboard/protectionplans/panel.py
karbor_dashboard/protectionplans/tables.py
karbor_dashboard/protectionplans/urls.py
karbor_dashboard/protectionplans/views.py
karbor_dashboard/protectionproviders/__init__.py
karbor_dashboard/protectionproviders/panel.py
karbor_dashboard/protectionproviders/tables.py
karbor_dashboard/protectionproviders/tabs.py
karbor_dashboard-1.5.1.dist-info/DESCRIPTION.rst
karbor_dashboard-1.5.1.dist-info/METADATA
karbor_dashboard-1.5.1.dist-info/RECORD
karbor_dashboard-1.5.1.dist-info/WHEEL
karbor_dashboard-1.5.1.dist-info/metadata.json
karbor_dashboard-1.5.1.dist-info/pbr.json
karbor_dashboard-1.5.1.dist-info/top_level.txt
