Metadata-Version: 2.0
Name: karbor-dashboard
Version: 1.5.1
Summary: Karbor Dashboard
Home-page: https://docs.openstack.org/karbor/latest/
Author: OpenStack
Author-email: openstack-discuss@lists.openstack.org
License: UNKNOWN
Platform: UNKNOWN
Classifier: Environment :: OpenStack
Classifier: Intended Audience :: Information Technology
Classifier: Intended Audience :: System Administrators
Classifier: License :: OSI Approved :: Apache Software License
Classifier: Operating System :: POSIX :: Linux
Classifier: Programming Language :: Python
Classifier: Programming Language :: Python :: Implementation :: CPython
Classifier: Programming Language :: Python :: 3 :: Only
Classifier: Programming Language :: Python :: 3
Classifier: Programming Language :: Python :: 3.6
Classifier: Programming Language :: Python :: 3.7
Requires-Python: >=3.6
Requires-Dist: Django (<3.0,>=2.2)
Requires-Dist: django-compressor (>=2.0)
Requires-Dist: django-pyscss (>=2.0.2)
Requires-Dist: horizon (>=17.1.0)
Requires-Dist: icalendar (>=4.0.2)
Requires-Dist: pbr (!=2.1.0,>=2.0.0)
Requires-Dist: python-karborclient (>=0.6.0)
